langchain_standard_tests/__init__.py
langchain_standard_tests/base.py
langchain_standard_tests/integration_tests/__init__.py
langchain_standard_tests/integration_tests/base_store.py
langchain_standard_tests/integration_tests/cache.py
langchain_standard_tests/integration_tests/chat_models.py
langchain_standard_tests/integration_tests/embeddings.py
langchain_standard_tests/integration_tests/indexer.py
langchain_standard_tests/integration_tests/tools.py
langchain_standard_tests/integration_tests/vectorstores.py
langchain_standard_tests/py.typed
langchain_standard_tests/unit_tests/__init__.py
langchain_standard_tests/unit_tests/chat_models.py
langchain_standard_tests/unit_tests/embeddings.py
langchain_standard_tests/unit_tests/tools.py
langchain_standard_tests/utils/__init__.py
langchain_standard_tests/utils/pydantic.py
langchain_base_tests-0.3.0.dist-info/METADATA
langchain_base_tests-0.3.0.dist-info/WHEEL
langchain_base_tests-0.3.0.dist-info/RECORD
