Metadata-Version: 2.1
Name: langchain-base-tests
Version: 0.3.0
Summary: Standard tests for LangChain implementations
Home-page: https://github.com/langchain-ai/langchain
License: MIT
Author: Erick Friis
Author-email: erick@langchain.dev
Requires-Python: >=3.9,<4.0
Classifier: License :: OSI Approved :: MIT License
Classifier: Programming Language :: Python :: 3
Classifier: Programming Language :: Python :: 3.9
Classifier: Programming Language :: Python :: 3.10
Classifier: Programming Language :: Python :: 3.11
Classifier: Programming Language :: Python :: 3.12
Requires-Dist: httpx (>=0.27.0,<0.28.0)
Requires-Dist: langchain-core (>=0.3.15,<0.4.0)
Requires-Dist: pytest (>=7,<9)
Requires-Dist: syrupy (>=4,<5)
Project-URL: Repository, https://github.com/langchain-ai/langchain
Project-URL: Source Code, https://github.com/langchain-ai/langchain/tree/master/libs/standard-tests
